{"lemma":"إِصْغاءاتٌ","slug":"إِصْغاءاتٌ","root":"ص.غ.#","root_slug":"ص-غ-_","root_link":"/words/roots/ص-غ-_","pos":"N","pos_camel":"noun","paradigm":[],"frequency_in_corpus":0,"cross_references":{"qac":{"found":false},"wiktextract":{"found":true,"entry_count":1,"pos_tags":["noun"],"has_etymology":false,"sense_count":1},"lanes":{"found":false}},"translations":null,"definition":{"source":"wiktextract","senses":[{"pos":"noun","gloss":"verbal noun of أَصْغَى (ʔaṣḡā) (form IV)","tags":["form-of","noun-from-verb"]}]},"etymology":null,"ipa":["/ʔisˤ.ɣaːʔ/"],"lanes_definition":null,"classical_definitions":null}