{"lemma":"طَشْتَيْ","slug":"طَشْتَيْ","root":"ط.ش.ت","root_slug":"ط-ش-ت","root_link":"/words/roots/ط-ش-ت","pos":"N","pos_camel":"noun","paradigm":[],"frequency_in_corpus":0,"cross_references":{"qac":{"found":false},"wiktextract":{"found":false},"lanes":{"found":true,"entry_ids":["n26725"],"search_url":"https://lanelexicon.com/?s=%D8%B7%D9%8E%D8%B4%D9%92%D8%AA%D9%8E%D9%8A%D9%92"}},"translations":null,"definition":null,"etymology":null,"ipa":null,"lanes_definition":{"source":"lanes","entries":[{"entry_id":"n26725","headword_ar":"طَشْتٌ","root":"T$t","body":[{"kind":"text","text":": see"},{"kind":"arabic","text_bw":"TasotN","text_ar":"طَسْتٌ"},{"kind":"text","text":"."}],"source_refs":[]}]}}