{"lemma":"عِبْرانِيّانِ","slug":"عِبْرانِيّانِ","root":"ع.ب.ر","root_slug":"ع-ب-ر","root_link":"/words/roots/ع-ب-ر","pos":"ADJ","pos_camel":"adj","paradigm":[],"frequency_in_corpus":0,"cross_references":{"qac":{"found":false},"wiktextract":{"found":true,"entry_count":2,"pos_tags":["adj","noun"],"has_etymology":false,"sense_count":2},"lanes":{"found":false}},"translations":null,"definition":{"source":"wiktextract","senses":[{"pos":"adj","gloss":"Hebrew, Hebraic"},{"pos":"noun","gloss":"a Hebrew"}]},"etymology":null,"ipa":null}