{"lemma":"مَحْبُوسُو","slug":"مَحْبُوسُو","root":"ح.ب.س","root_slug":"ح-ب-س","root_link":"/words/roots/ح-ب-س","pos":"N","pos_camel":"noun","paradigm":[],"frequency_in_corpus":0,"cross_references":{"qac":{"found":false},"wiktextract":{"found":true,"entry_count":1,"pos_tags":["adj"],"has_etymology":true,"sense_count":2},"lanes":{"found":true,"entry_ids":["n6918"],"search_url":"https://lanelexicon.com/?s=%D9%85%D9%8E%D8%AD%D9%92%D8%A8%D9%8F%D9%88%D8%B3%D9%8F%D9%88"}},"translations":null,"definition":{"source":"wiktextract","senses":[{"pos":"adj","gloss":"passive participle of حَبَسَ (ḥabasa)","tags":["form-of","participle","passive"]},{"pos":"adj","gloss":"passive participle of حَبَسَ (ḥabasa); imprisoned, incarcerated, jailed"}]},"etymology":{"source":"wiktextract","text":"Derived from the passive participle of the verb حَبَسَ (ḥabasa, “to imprison”)."},"ipa":["/maħ.buːs/"],"lanes_definition":{"source":"lanes","entries":[{"entry_id":"n6918","headword_ar":"مَحْبُوسٌ","root":"Hbs","body":[{"kind":"text","text":": see"},{"kind":"arabic","text_bw":"HabiysN","text_ar":"حَبِيسٌ"},{"kind":"text","text":", in three places."}],"source_refs":[]}]},"classical_definitions":null}