{"surface":"حَضَرَهُ","slug":"حَضَرَهُ","occurrence_count":29,"occurrence_paths":["/books/al-amali-saduq:50:1","/books/al-istibsar:1:113:5","/books/al-kafi:1:4:124:1","/books/al-kafi:1:4:64:6","/books/al-kafi:1:4:66:2","/books/al-kafi:1:4:68:1","/books/al-kafi:1:4:68:2","/books/al-kafi:1:4:92:3","/books/al-kafi:7:1:2:7","/books/al-kafi:7:1:6:1","/books/al-kafi:7:6:6:2","/books/man-la-yahduruhu-al-faqih:1:24:22","/books/man-la-yahduruhu-al-faqih:1:24:25","/books/man-la-yahduruhu-al-faqih:2:3:41:3","/books/man-la-yahduruhu-al-faqih:3:3:25:44","/books/man-la-yahduruhu-al-faqih:4:105:4","/books/man-la-yahduruhu-al-faqih:4:127:5","/books/tahdhib-al-ahkam:1:28:10","/books/tahdhib-al-ahkam:1:28:62","/books/tahdhib-al-ahkam:1:9:11"],"morphology":{"lemma_slug":"حَضَرٌ","root":"ح.ض.ر","root_slug":"ح-ض-ر","pos":"N","pos_camel":"noun","clitics":{"enc0":"3ms_poss"}},"lemma_link":"/words/lemmas/حَضَرٌ","root_link":"/words/roots/ح-ض-ر"}