{"surface":"لِلصَّلَاةِ","slug":"لِلصَّلَاةِ","occurrence_count":75,"occurrence_paths":["/books/al-amali-saduq:1:15","/books/al-amali-saduq:61:5","/books/al-amali-saduq:65:2","/books/al-amali-saduq:80:16","/books/al-amali-saduq:81:11","/books/al-amali-saduq:86:5","/books/al-amali-saduq:92:7","/books/al-istibsar:1:10:4","/books/al-istibsar:1:11:1","/books/al-istibsar:1:142:3","/books/al-istibsar:1:142:8","/books/al-istibsar:1:144:5","/books/al-istibsar:1:148:2","/books/al-istibsar:1:14:3","/books/al-istibsar:1:158:10","/books/al-istibsar:1:207:4","/books/al-istibsar:1:24:2","/books/al-istibsar:1:257:5","/books/al-istibsar:1:25:39","/books/al-istibsar:1:25:42","/books/al-istibsar:1:54:6","/books/al-istibsar:1:5:1","/books/al-istibsar:1:5:2","/books/al-istibsar:1:71:2","/books/al-kafi:1:4:124:1","/books/al-kafi:1:4:125:3","/books/al-kafi:3:1:4:1","/books/al-kafi:3:4:3:6","/books/man-la-yahduruhu-al-faqih:1:10:1","/books/man-la-yahduruhu-al-faqih:1:26:1","/books/man-la-yahduruhu-al-faqih:1:2:7","/books/man-la-yahduruhu-al-faqih:1:30:8","/books/man-la-yahduruhu-al-faqih:1:45:3","/books/man-la-yahduruhu-al-faqih:1:45:49","/books/man-la-yahduruhu-al-faqih:1:8:3","/books/man-la-yahduruhu-al-faqih:4:12:30","/books/tahdhib-al-ahkam:10:9:18","/books/tahdhib-al-ahkam:1:16:24","/books/tahdhib-al-ahkam:1:19:2","/books/tahdhib-al-ahkam:1:19:30","/books/tahdhib-al-ahkam:1:19:49","/books/tahdhib-al-ahkam:1:19:57","/books/tahdhib-al-ahkam:1:21:83","/books/tahdhib-al-ahkam:1:22:52","/books/tahdhib-al-ahkam:1:23:14","/books/tahdhib-al-ahkam:1:23:15","/books/tahdhib-al-ahkam:1:23:41","/books/tahdhib-al-ahkam:1:25:22","/books/tahdhib-al-ahkam:1:25:9","/books/tahdhib-al-ahkam:1:26:33","/books/tahdhib-al-ahkam:1:27:22","/books/tahdhib-al-ahkam:1:31:31","/books/tahdhib-al-ahkam:1:32:11","/books/tahdhib-al-ahkam:1:32:36","/books/tahdhib-al-ahkam:1:33:8","/books/tahdhib-al-ahkam:1:36:14","/books/tahdhib-al-ahkam:1:36:4","/books/tahdhib-al-ahkam:1:37:16","/books/tahdhib-al-ahkam:1:37:34","/books/tahdhib-al-ahkam:1:37:44","/books/tahdhib-al-ahkam:2:13:25","/books/tahdhib-al-ahkam:2:13:26"],"morphology":{"lemma_slug":"صَلاةٍ","root":"ص.ل.#","pos":"N","pos_camel":"noun","clitics":{"prc0":"Al_det","prc1":"li_prep"}},"lemma_link":"/words/lemmas/صَلاةٍ"}